fava_budgets/__init__.py
fava_budgets/actuals.py
fava_budgets/beancount_plugin.py
fava_budgets/fava_plugin.py
fava_budgets/services/AssetBudgetReportService.py
fava_budgets/services/BudgetReportServices.py
fava_budgets/services/Loaders.py
fava_budgets/services/NestedDictionary.py
fava_budgets/services/Summary.py
fava_budgets/services/__init__.py
fava_custom_budgets-0.0.1.dist-info/METADATA
fava_custom_budgets-0.0.1.dist-info/WHEEL
fava_custom_budgets-0.0.1.dist-info/top_level.txt
fava_custom_budgets-0.0.1.dist-info/RECORD
