Metadata-Version: 2.2
Name: fava-custom-budgets
Version: 0.0.1
Summary: A fava plugin to report on income/expense budgets and savings budgets
Author-email: Tino Fuhrmann <tino.fuhrmann1@gmail.com>
Project-URL: Homepage, https://github.com/TiFu/fava_budgets
Project-URL: Issues, https://github.com/TiFu/fava_budgets/issues
Classifier: Programming Language :: Python :: 3
Classifier: License :: OSI Approved :: MIT License
Classifier: Operating System :: OS Independent
Requires-Python: >=3.8
Requires-Dist: fava>=1.26.1
Requires-Dist: pyyaml>=6.0.1
Requires-Dist: beanquery>=0.1.0
